{
    "id":  "travail-force",
    "prerequisites":  [
                          "Notions de base"
                      ],
    "keywords":  [
                     "travail",
                     "force"
                 ],
    "realWorldApp":  "Applications pratiques",
    "level":  "premiere",
    "xpReward":  150,
    "objectives":  [
                       "Comprendre les concepts fondamentaux",
                       "Appliquer les méthodes"
                   ],
    "subject":  "math",
    "chapter":  "Chapitre",
    "difficulty":  3,
    "title":  "Travail Force",
    "duration":  8
}
